systolic_array/pe.sv
module pe #(
    parameter DATA_WIDTH = 8,
    parameter ACC_WIDTH  = 32
)(
    input  logic clk,
    input  logic reset,
    input  logic clear_acc,

    input  logic signed [DATA_WIDTH-1:0] activation_in,
    input  logic                         activation_valid_in,

    input  logic signed [DATA_WIDTH-1:0] weight_in,
    input  logic                         weight_valid_in,

    output logic signed [DATA_WIDTH-1:0] activation_out,
    output logic                         activation_valid_out,

    output logic signed [DATA_WIDTH-1:0] weight_out,
    output logic                         weight_valid_out,
    
    output logic signed [ACC_WIDTH-1:0] partial_sum
);

    localparam PRODUCT_WIDTH = 2 * DATA_WIDTH;
    logic signed [PRODUCT_WIDTH-1:0] product;
    assign product = activation_in * weight_in;

    always_ff @(posedge clk) begin
        if (reset) begin
            activation_out       <= '0;
            activation_valid_out <= 1'b0;
            weight_out           <= '0;
            weight_valid_out     <= 1'b0;
            partial_sum          <= '0;
        end
        else begin
            // Pass activation to the right
            activation_out       <= activation_in;
            activation_valid_out <= activation_valid_in;

            // Pass weight downward
            weight_out           <= weight_in;
            weight_valid_out     <= weight_valid_in;

            // Control the stationary accumulator
            if (clear_acc) begin
                if(activation_valid_in && weight_valid_in)
                    partial_sum <= product;
                else
                    partial_sum <= '0;
            end
            else if (activation_valid_in && weight_valid_in) begin
                partial_sum <= partial_sum + product;
            end
        end
    end

endmodule

systolic_array_output_stationary/pe_tb.sv
`timescale 1ns/1ps

module pe_tb;

    // ------------------------------------------------------------
    // Parameters
    // ------------------------------------------------------------
    localparam DATA_WIDTH = 8;
    localparam ACC_WIDTH  = 32;

    // ------------------------------------------------------------
    // DUT inputs
    // ------------------------------------------------------------
    logic clk;
    logic reset;
    logic clear_acc;

    logic signed [DATA_WIDTH-1:0] activation_in;
    logic                         activation_valid_in;

    logic signed [DATA_WIDTH-1:0] weight_in;
    logic                         weight_valid_in;

    // ------------------------------------------------------------
    // DUT outputs
    // ------------------------------------------------------------
    logic signed [DATA_WIDTH-1:0] activation_out;
    logic                         activation_valid_out;

    logic signed [DATA_WIDTH-1:0] weight_out;
    logic                         weight_valid_out;

    logic signed [ACC_WIDTH-1:0] partial_sum;

    // ------------------------------------------------------------
    // Testbench bookkeeping
    // ------------------------------------------------------------
    logic signed [ACC_WIDTH-1:0] expected_partial_sum;

    integer error_count;
    integer i;

    logic signed [DATA_WIDTH-1:0] random_activation;
    logic signed [DATA_WIDTH-1:0] random_weight;
    logic                         random_activation_valid;
    logic                         random_weight_valid;
    logic                         random_clear;
    logic                         random_reset;


    // ============================================================
    // Instantiate DUT
    // ============================================================

    pe #(
        .DATA_WIDTH(DATA_WIDTH),
        .ACC_WIDTH(ACC_WIDTH)
    ) dut (
        .clk(clk),
        .reset(reset),
        .clear_acc(clear_acc),

        .activation_in(activation_in),
        .activation_valid_in(activation_valid_in),

        .weight_in(weight_in),
        .weight_valid_in(weight_valid_in),

        .activation_out(activation_out),
        .activation_valid_out(activation_valid_out),

        .weight_out(weight_out),
        .weight_valid_out(weight_valid_out),

        .partial_sum(partial_sum)
    );


    // ============================================================
    // Clock generation
    //
    // 10 ns clock period:
    //
    //      __    __    __
    // clk    |__|  |__|
    //
    //      5ns 5ns
    // ============================================================

    initial begin
        clk = 1'b0;
    end

    always #5 clk = ~clk;


    // ============================================================
    // Task: apply one cycle and automatically check the result
    // ============================================================

    task automatic apply_and_check(
        input logic                         rst,
        input logic                         clr,
        input logic signed [DATA_WIDTH-1:0] act,
        input logic                         act_valid,
        input logic signed [DATA_WIDTH-1:0] wgt,
        input logic                         wgt_valid,
        input string                        test_name
    );

        logic signed [(2*DATA_WIDTH)-1:0] expected_product;

        begin

            // ----------------------------------------------------
            // Change inputs on the falling edge.
            //
            // This gives them plenty of time to settle before
            // the PE samples them on the next rising edge.
            // ----------------------------------------------------
            @(negedge clk);

            reset               = rst;
            clear_acc           = clr;

            activation_in       = act;
            activation_valid_in = act_valid;

            weight_in           = wgt;
            weight_valid_in     = wgt_valid;

            expected_product = act * wgt;


            // ----------------------------------------------------
            // DUT samples inputs here
            // ----------------------------------------------------
            @(posedge clk);

            // Give nonblocking assignments time to update
            #1;


            // ====================================================
            // Reference model for partial_sum
            // ====================================================

            if (rst) begin
                expected_partial_sum = '0;
            end

            else if (clr) begin

                if (act_valid && wgt_valid)
                    expected_partial_sum = expected_product;
                else
                    expected_partial_sum = '0;

            end

            else if (act_valid && wgt_valid) begin

                expected_partial_sum =
                    expected_partial_sum + expected_product;

            end


            // ====================================================
            // Check activation forwarding
            // ====================================================

            if (rst) begin

                if (activation_out !== '0) begin
                    $error(
                        "%s: activation_out should reset to 0, got %0d",
                        test_name,
                        activation_out
                    );
                    error_count++;
                end

                if (activation_valid_out !== 1'b0) begin
                    $error(
                        "%s: activation_valid_out should reset to 0",
                        test_name
                    );
                    error_count++;
                end

            end

            else begin

                if (activation_out !== act) begin
                    $error(
                        "%s: activation forwarding failed. Expected %0d, got %0d",
                        test_name,
                        act,
                        activation_out
                    );
                    error_count++;
                end

                if (activation_valid_out !== act_valid) begin
                    $error(
                        "%s: activation valid forwarding failed. Expected %b, got %b",
                        test_name,
                        act_valid,
                        activation_valid_out
                    );
                    error_count++;
                end

            end


            // ====================================================
            // Check weight forwarding
            // ====================================================

            if (rst) begin

                if (weight_out !== '0) begin
                    $error(
                        "%s: weight_out should reset to 0, got %0d",
                        test_name,
                        weight_out
                    );
                    error_count++;
                end

                if (weight_valid_out !== 1'b0) begin
                    $error(
                        "%s: weight_valid_out should reset to 0",
                        test_name
                    );
                    error_count++;
                end

            end

            else begin

                if (weight_out !== wgt) begin
                    $error(
                        "%s: weight forwarding failed. Expected %0d, got %0d",
                        test_name,
                        wgt,
                        weight_out
                    );
                    error_count++;
                end

                if (weight_valid_out !== wgt_valid) begin
                    $error(
                        "%s: weight valid forwarding failed. Expected %b, got %b",
                        test_name,
                        wgt_valid,
                        weight_valid_out
                    );
                    error_count++;
                end

            end


            // ====================================================
            // Check partial sum
            // ====================================================

            if (partial_sum !== expected_partial_sum) begin

                $error(
                    "%s: partial_sum incorrect. Expected %0d, got %0d",
                    test_name,
                    expected_partial_sum,
                    partial_sum
                );

                error_count++;

            end

            else begin

                $display(
                    "PASS: %-35s | A=%4d V=%b | W=%4d V=%b | clear=%b reset=%b | psum=%0d",
                    test_name,
                    act,
                    act_valid,
                    wgt,
                    wgt_valid,
                    clr,
                    rst,
                    partial_sum
                );

            end

        end

    endtask


    // ============================================================
    // Main test sequence
    // ============================================================

    initial begin

        // --------------------------------------------------------
        // Initial values
        // --------------------------------------------------------
        reset               = 1'b0;
        clear_acc           = 1'b0;

        activation_in       = '0;
        activation_valid_in = 1'b0;

        weight_in           = '0;
        weight_valid_in     = 1'b0;

        expected_partial_sum = '0;
        error_count          = 0;


        $display("");
        $display("==========================================");
        $display("       Starting PE Testbench");
        $display("==========================================");
        $display("");


        // ========================================================
        // TEST 1: RESET
        // ========================================================

        apply_and_check(
            1'b1,
            1'b0,
            8'sd50,
            1'b1,
            -8'sd4,
            1'b1,
            "Reset clears PE"
        );


        // ========================================================
        // TEST 2: IDLE AFTER RESET
        // ========================================================

        apply_and_check(
            1'b0,
            1'b0,
            8'sd0,
            1'b0,
            8'sd0,
            1'b0,
            "Idle after reset"
        );


        // ========================================================
        // TEST 3: CLEAR + FIRST PRODUCT
        //
        // 3 * 4 = 12
        // ========================================================

        apply_and_check(
            1'b0,
            1'b1,
            8'sd3,
            1'b1,
            8'sd4,
            1'b1,
            "Start accumulation: 3 * 4"
        );


        // ========================================================
        // TEST 4: SECOND PRODUCT
        //
        // 12 + (2 * 5)
        // = 22
        // ========================================================

        apply_and_check(
            1'b0,
            1'b0,
            8'sd2,
            1'b1,
            8'sd5,
            1'b1,
            "Accumulate: + 2 * 5"
        );


        // ========================================================
        // TEST 5: THIRD PRODUCT
        //
        // 22 + (7 * 3)
        // = 43
        // ========================================================

        apply_and_check(
            1'b0,
            1'b0,
            8'sd7,
            1'b1,
            8'sd3,
            1'b1,
            "Accumulate: + 7 * 3"
        );


        // ========================================================
        // TEST 6: ACTIVATION VALID, WEIGHT INVALID
        //
        // No MAC should occur.
        // partial_sum should remain 43.
        //
        // Data itself should STILL be forwarded.
        // ========================================================

        apply_and_check(
            1'b0,
            1'b0,
            8'sd20,
            1'b1,
            8'sd10,
            1'b0,
            "Weight invalid - hold psum"
        );


        // ========================================================
        // TEST 7: WEIGHT VALID, ACTIVATION INVALID
        // ========================================================

        apply_and_check(
            1'b0,
            1'b0,
            8'sd10,
            1'b0,
            8'sd11,
            1'b1,
            "Activation invalid - hold psum"
        );


        // ========================================================
        // TEST 8: BOTH INVALID
        // ========================================================

        apply_and_check(
            1'b0,
            1'b0,
            8'sd100,
            1'b0,
            -8'sd100,
            1'b0,
            "Both invalid - hold psum"
        );


        // ========================================================
        // TEST 9: CLEAR WITHOUT VALID DATA
        //
        // clear_acc = 1
        // No valid operands
        //
        // partial_sum should become 0
        // ========================================================

        apply_and_check(
            1'b0,
            1'b1,
            8'sd5,
            1'b0,
            8'sd5,
            1'b0,
            "Clear accumulator without MAC"
        );


        // ========================================================
        // TEST 10: POSITIVE * NEGATIVE
        //
        // 7 * -3 = -21
        // ========================================================

        apply_and_check(
            1'b0,
            1'b1,
            8'sd7,
            1'b1,
            -8'sd3,
            1'b1,
            "Signed: positive * negative"
        );


        // ========================================================
        // TEST 11: NEGATIVE * NEGATIVE
        //
        // -2 * -4 = 8
        //
        // old psum = -21
        //
        // -21 + 8 = -13
        // ========================================================

        apply_and_check(
            1'b0,
            1'b0,
            -8'sd2,
            1'b1,
            -8'sd4,
            1'b1,
            "Signed: negative * negative"
        );


        // ========================================================
        // TEST 12: NEGATIVE * POSITIVE
        //
        // -5 * 6 = -30
        //
        // -13 - 30 = -43
        // ========================================================

        apply_and_check(
            1'b0,
            1'b0,
            -8'sd5,
            1'b1,
            8'sd6,
            1'b1,
            "Signed: negative * positive"
        );


        // ========================================================
        // TEST 13: CLEAR STARTS A NEW RESULT
        //
        // Old psum should be discarded.
        //
        // 10 * 10 = 100
        // ========================================================

        apply_and_check(
            1'b0,
            1'b1,
            8'sd10,
            1'b1,
            8'sd10,
            1'b1,
            "Clear and immediately MAC"
        );


        // ========================================================
        // TEST 14: MAXIMUM POSITIVE VALUES
        //
        // 127 * 127 = 16129
        // ========================================================

        apply_and_check(
            1'b0,
            1'b1,
            8'sd127,
            1'b1,
            8'sd127,
            1'b1,
            "Maximum positive operands"
        );


        // ========================================================
        // TEST 15: MOST NEGATIVE VALUES
        //
        // -128 * -128 = 16384
        //
        // This is a particularly important multiplication-width
        // test because 16384 requires the full product width.
        // ========================================================

        apply_and_check(
            1'b0,
            1'b1,
            8'sh80,
            1'b1,
            8'sh80,
            1'b1,
            "Minimum signed operands"
        );


        // ========================================================
        // TEST 16: -128 * 127
        //
        // = -16256
        // ========================================================

        apply_and_check(
            1'b0,
            1'b1,
            8'sh80,
            1'b1,
            8'sd127,
            1'b1,
            "Signed boundary mixed signs"
        );


        // ========================================================
        // TEST 17: RESET HAS HIGHEST PRIORITY
        //
        // reset = 1
        // clear = 1
        // both operands valid
        //
        // Entire PE should reset.
        // ========================================================

        apply_and_check(
            1'b1,
            1'b1,
            8'sd20,
            1'b1,
            8'sd20,
            1'b1,
            "Reset priority over clear/MAC"
        );


        // ========================================================
        // TEST 18: RANDOMIZED TESTING
        //
        // The exact same reference model is used to predict
        // what the DUT should do.
        // ========================================================

        $display("");
        $display("------------------------------------------");
        $display("Starting randomized tests");
        $display("------------------------------------------");
        $display("");

        for (i = 0; i < 100; i++) begin

            // Random 8-bit patterns automatically include
            // both positive and negative signed numbers.
            random_activation = $urandom;
            random_weight     = $urandom;

            random_activation_valid = $urandom_range(0, 1);
            random_weight_valid     = $urandom_range(0, 1);

            // Roughly 10% of cycles clear the accumulator
            random_clear = ($urandom_range(0, 9) == 0);

            // Roughly 2% of cycles perform a full reset
            random_reset = ($urandom_range(0, 49) == 0);

            apply_and_check(
                random_reset,
                random_clear,
                random_activation,
                random_activation_valid,
                random_weight,
                random_weight_valid,
                $sformatf("Random test %0d", i)
            );

        end


        // ========================================================
        // Final result
        // ========================================================

        $display("");
        $display("==========================================");

        if (error_count == 0) begin
            $display("ALL TESTS PASSED!");
        end
        else begin
            $display("TESTBENCH FAILED WITH %0d ERRORS", error_count);
        end

        $display("==========================================");
        $display("");

        $finish;

    end


    // ============================================================
    // Waveform generation
    // ============================================================

    initial begin

        $dumpfile("pe_tb.vcd");
        $dumpvars(0, pe_tb);

    end

endmodule

systolic_array/pe_tb.vcd
$date
	Sun Aug 16 14:20:42 2026
$end
$version
	Icarus Verilog
$end
$timescale
	1ps
$end
$scope module pe_tb $end
$var wire 1 ! weight_valid_out $end
$var wire 8 " weight_out [7:0] $end
$var wire 32 # partial_sum [31:0] $end
$var wire 1 $ activation_valid_out $end
$var wire 8 % activation_out [7:0] $end
$var parameter 32 & ACC_WIDTH $end
$var parameter 32 ' DATA_WIDTH $end
$var reg 8 ( activation_in [7:0] $end
$var reg 1 ) activation_valid_in $end
$var reg 1 * clear_acc $end
$var reg 1 + clk $end
$var reg 32 , expected_partial_sum [31:0] $end
$var reg 8 - random_activation [7:0] $end
$var reg 1 . random_activation_valid $end
$var reg 1 / random_clear $end
$var reg 1 0 random_reset $end
$var reg 8 1 random_weight [7:0] $end
$var reg 1 2 random_weight_valid $end
$var reg 1 3 reset $end
$var reg 8 4 weight_in [7:0] $end
$var reg 1 5 weight_valid_in $end
$var integer 32 6 error_count [31:0] $end
$var integer 32 7 i [31:0] $end
$scope module dut $end
$var wire 8 8 activation_in [7:0] $end
$var wire 1 ) activation_valid_in $end
$var wire 1 * clear_acc $end
$var wire 1 + clk $end
$var wire 1 3 reset $end
$var wire 8 9 weight_in [7:0] $end
$var wire 1 5 weight_valid_in $end
$var wire 16 : product [15:0] $end
$var parameter 32 ; ACC_WIDTH $end
$var parameter 32 < DATA_WIDTH $end
$var parameter 64 = PRODUCT_WIDTH $end
$var reg 8 > activation_out [7:0] $end
$var reg 1 $ activation_valid_out $end
$var reg 32 ? partial_sum [31:0] $end
$var reg 8 @ weight_out [7:0] $end
$var reg 1 ! weight_valid_out $end
$upscope $end
$scope task apply_and_check $end
$upscope $end
$upscope $end
$enddefinitions $end
$comment Show the parameter values. $end
$dumpall
b10000 =
b1000 <
b100000 ;
b1000 '
b100000 &
$end
#0
$dumpvars
bx @
bx ?
bx >
b0 :
b0 9
b0 8
bx 7
b0 6
05
b0 4
03
x2
bx 1
x0
x/
x.
bx -
b0 ,
0+
0*
0)
b0 (
bx %
x$
bx #
bx "
x!
$end
#5000
0!
b0 "
b0 @
0$
b0 %
b0 >
1+
#10000
15
b1111111100111000 :
b11111100 4
b11111100 9
1)
b110010 (
b110010 8
13
0+
#15000
b0 #
b0 ?
1+
#20000
05
b0 4
b0 9
0)
b0 :
b0 (
b0 8
03
0+
#25000
1+
#30000
15
b1100 :
b100 4
b100 9
1)
b11 (
b11 8
1*
0+
#35000
b1100 #
b1100 ?
1!
b100 "
b100 @
1$
b11 %
b11 >
1+
#36000
b1100 ,
#40000
b101 4
b101 9
b1010 :
b10 (
b10 8
0*
0+
#45000
b10110 #
b10110 ?
b101 "
b101 @
b10 %
b10 >
1+
#46000
b10110 ,
#50000
b11 4
b11 9
b10101 :
b111 (
b111 8
0+
#55000
b101011 #
b101011 ?
b11 "
b11 @
b111 %
b111 >
1+
#56000
b101011 ,
#60000
05
b1010 4
b1010 9
b11001000 :
b10100 (
b10100 8
0+
#65000
0!
b1010 "
b1010 @
b10100 %
b10100 >
1+
#70000
15
b1011 4
b1011 9
0)
b1101110 :
b1010 (
b1010 8
0+
#75000
1!
b1011 "
b1011 @
0$
b1010 %
b1010 >
1+
#80000
05
b10011100 4
b10011100 9
b1101100011110000 :
b1100100 (
b1100100 8
0+
#85000
0!
b10011100 "
b10011100 @
b1100100 %
b1100100 >
1+
#90000
b101 4
b101 9
b11001 :
b101 (
b101 8
1*
0+
#95000
b0 #
b0 ?
b101 "
b101 @
b101 %
b101 >
1+
#96000
b0 ,
#100000
15
b11111101 4
b11111101 9
1)
b1111111111101011 :
b111 (
b111 8
0+
#105000
b11111111111111111111111111101011 #
b11111111111111111111111111101011 ?
1!
b11111101 "
b11111101 @
1$
b111 %
b111 >
1+
#106000
b11111111111111111111111111101011 ,
#110000
b11111100 4
b11111100 9
b1000 :
b11111110 (
b11111110 8
0*
0+
#115000
b11111111111111111111111111110011 #
b11111111111111111111111111110011 ?
b11111100 "
b11111100 @
b11111110 %
b11111110 >
1+
#116000
b11111111111111111111111111110011 ,
#120000
b110 4
b110 9
b1111111111100010 :
b11111011 (
b11111011 8
0+
#125000
b11111111111111111111111111010101 #
b11111111111111111111111111010101 ?
b110 "
b110 @
b11111011 %
b11111011 >
1+
#126000
b11111111111111111111111111010101 ,
#130000
b1010 4
b1010 9
b1100100 :
b1010 (
b1010 8
1*
0+
#135000
b1100100 #
b1100100 ?
b1010 "
b1010 @
b1010 %
b1010 >
1+
#136000
b1100100 ,
#140000
b1111111 4
b1111111 9
b11111100000001 :
b1111111 (
b1111111 8
0+
#145000
b11111100000001 #
b11111100000001 ?
b1111111 "
b1111111 @
b1111111 %
b1111111 >
1+
#146000
b11111100000001 ,
#150000
b10000000 4
b10000000 9
b100000000000000 :
b10000000 (
b10000000 8
0+
#155000
b100000000000000 #
b100000000000000 ?
b10000000 "
b10000000 @
b10000000 %
b10000000 >
1+
#156000
b100000000000000 ,
#160000
b1100000010000000 :
b1111111 4
b1111111 9
0+
#165000
b11111111111111111100000010000000 #
b11111111111111111100000010000000 ?
b1111111 "
b1111111 @
1+
#166000
b11111111111111111100000010000000 ,
#170000
b10100 4
b10100 9
b110010000 :
b10100 (
b10100 8
13
0+
#175000
b0 #
b0 ?
0!
b0 "
b0 @
0$
b0 %
b0 >
1+
#176000
00
0/
02
0.
b10000001 1
b100100 -
b0 7
b0 ,
#180000
05
b10000001 4
b10000001 9
0)
b1110111000100100 :
b100100 (
b100100 8
0*
03
0+
#185000
b10000001 "
b10000001 @
b100100 %
b100100 >
1+
#186000
12
1.
b10010 1
b1100101 -
b1 7
#190000
15
b10010 4
b10010 9
1)
b11100011010 :
b1100101 (
b1100101 8
0+
#195000
b11100011010 #
b11100011010 ?
1!
b10010 "
b10010 @
1$
b1100101 %
b1100101 >
1+
#196000
02
b10001100 1
b11101101 -
b10 7
b11100011010 ,
#200000
05
b10001100 4
b10001100 9
b100010011100 :
b11101101 (
b11101101 8
0+
#205000
0!
b10001100 "
b10001100 @
b11101101 %
b11101101 >
1+
#206000
12
0.
b1110111 1
b11100101 -
b11 7
#210000
15
b1110111 4
b1110111 9
0)
b1111001101110011 :
b11100101 (
b11100101 8
0+
#215000
1!
b1110111 "
b1110111 @
0$
b11100101 %
b11100101 >
1+
#216000
1/
02
1.
b11000101 1
b11101000 -
b100 7
#220000
05
b11000101 4
b11000101 9
1)
b10110001000 :
b11101000 (
b11101000 8
1*
0+
#225000
b0 #
b0 ?
0!
b11000101 "
b11000101 @
1$
b11101000 %
b11101000 >
1+
#226000
0/
12
0.
b1010 1
b1100011 -
b101 7
b0 ,
#230000
15
b1010 4
b1010 9
0)
b1111011110 :
b1100011 (
b1100011 8
0*
0+
#235000
1!
b1010 "
b1010 @
0$
b1100011 %
b1100011 >
1+
#236000
02
b10011 1
b10010110 -
b110 7
#240000
05
b10011 4
b10011 9
b1111100000100010 :
b10010110 (
b10010110 8
0+
#245000
0!
b10011 "
b10011 @
b10010110 %
b10010110 >
1+
#246000
1.
b10101110 1
b10 -
b111 7
#250000
b10101110 4
b10101110 9
1)
b1111111101011100 :
b10 (
b10 8
0+
#255000
b10101110 "
b10101110 @
1$
b10 %
b10 >
1+
#256000
12
b111100 1
b11001010 -
b1000 7
#260000
15
b111100 4
b111100 9
b1111001101011000 :
b11001010 (
b11001010 8
0+
#265000
b11111111111111111111001101011000 #
b11111111111111111111001101011000 ?
1!
b111100 "
b111100 @
b11001010 %
b11001010 >
1+
#266000
b10001001 1
b1111000 -
b1001 7
b11111111111111111111001101011000 ,
#270000
b10001001 4
b10001001 9
b1100100000111000 :
b1111000 (
b1111000 8
0+
#275000
b11111111111111111011101110010000 #
b11111111111111111011101110010000 ?
b10001001 "
b10001001 @
b1111000 %
b1111000 >
1+
#276000
02
0.
b101010 1
b10111100 -
b1010 7
b11111111111111111011101110010000 ,
#280000
05
b101010 4
b101010 9
0)
b1111010011011000 :
b10111100 (
b10111100 8
0+
#285000
0!
b101010 "
b101010 @
0$
b10111100 %
b10111100 >
1+
#286000
12
b111010 1
b111011 -
b1011 7
#290000
15
b111010 4
b111010 9
b110101011110 :
b111011 (
b111011 8
0+
#295000
1!
b111010 "
b111010 @
b111011 %
b111011 >
1+
#296000
1.
b1001100 1
b1100010 -
b1100 7
#300000
b1001100 4
b1001100 9
1)
b1110100011000 :
b1100010 (
b1100010 8
0+
#305000
b11111111111111111101100010101000 #
b11111111111111111101100010101000 ?
b1001100 "
b1001100 @
1$
b1100010 %
b1100010 >
1+
#306000
0.
b1011100 1
b10011111 -
b1101 7
b11111111111111111101100010101000 ,
#310000
b1011100 4
b1011100 9
0)
b1101110100100100 :
b10011111 (
b10011111 8
0+
#315000
b1011100 "
b1011100 @
0$
b10011111 %
b10011111 >
1+
#316000
1.
b1010001 1
b11010111 -
b1110 7
#320000
b1010001 4
b1010001 9
1)
b1111001100000111 :
b11010111 (
b11010111 8
0+
#325000
b11111111111111111100101110101111 #
b11111111111111111100101110101111 ?
b1010001 "
b1010001 @
1$
b11010111 %
b11010111 >
1+
#326000
02
b111101 1
b1110111 -
b1111 7
b11111111111111111100101110101111 ,
#330000
05
b111101 4
b111101 9
b1110001011011 :
b1110111 (
b1110111 8
0+
#335000
0!
b111101 "
b111101 @
b1110111 %
b1110111 >
1+
#336000
b11010011 1
b11111 -
b10000 7
#340000
b11010011 4
b11010011 9
b1111101010001101 :
b11111 (
b11111 8
0+
#345000
b11010011 "
b11010011 @
b11111 %
b11111 >
1+
#346000
b101010 1
b111111 -
b10001 7
#350000
b101010 4
b101010 9
b101001010110 :
b111111 (
b111111 8
0+
#355000
b101010 "
b101010 @
b111111 %
b111111 >
1+
#356000
1/
b100110 1
b11111010 -
b10010 7
#360000
b100110 4
b100110 9
b1111111100011100 :
b11111010 (
b11111010 8
1*
0+
#365000
b0 #
b0 ?
b100110 "
b100110 @
b11111010 %
b11111010 >
1+
#366000
0/
b1000100 1
b1011111 -
b10011 7
b0 ,
#370000
b1000100 4
b1000100 9
b1100100111100 :
b1011111 (
b1011111 8
0*
0+
#375000
b1000100 "
b1000100 @
b1011111 %
b1011111 >
1+
#376000
0.
b11101101 1
b101001 -
b10100 7
#380000
b11101101 4
b11101101 9
0)
b1111110011110101 :
b101001 (
b101001 8
0+
#385000
b11101101 "
b11101101 @
0$
b101001 %
b101001 >
1+
#386000
12
b1000100 1
b1111001 -
b10101 7
#390000
15
b1000100 4
b1000100 9
b10000000100100 :
b1111001 (
b1111001 8
0+
#395000
1!
b1000100 "
b1000100 @
b1111001 %
b1111001 >
1+
#396000
02
b10011010 1
b11011100 -
b10110 7
#400000
05
b10011010 4
b10011010 9
b111001011000 :
b11011100 (
b11011100 8
0+
#405000
0!
b10011010 "
b10011010 @
b11011100 %
b11011100 >
1+
#406000
1.
b1010 1
b1100111 -
b10111 7
#410000
b1010 4
b1010 9
1)
b10000000110 :
b1100111 (
b1100111 8
0+
#415000
b1010 "
b1010 @
1$
b1100111 %
b1100111 >
1+
#416000
0.
b10010011 1
b10010100 -
b11000 7
#420000
b10010011 4
b10010011 9
0)
b10110111111100 :
b10010100 (
b10010100 8
0+
#425000
b10010011 "
b10010011 @
0$
b10010100 %
b10010100 >
1+
#426000
12
b1101101 1
b11011001 -
b11001 7
#430000
15
b1101101 4
b1101101 9
b1110111101100101 :
b11011001 (
b11011001 8
0+
#435000
1!
b1101101 "
b1101101 @
b11011001 %
b11011001 >
1+
#436000
1.
b100 1
b1000110 -
b11010 7
#440000
b100 4
b100 9
1)
b100011000 :
b1000110 (
b1000110 8
0+
#445000
b100011000 #
b100011000 ?
b100 "
b100 @
1$
b1000110 %
b1000110 >
1+
#446000
1/
02
0.
b101101 1
b101000 -
b11011 7
b100011000 ,
#450000
05
b101101 4
b101101 9
0)
b11100001000 :
b101000 (
b101000 8
1*
0+
#455000
b0 #
b0 ?
0!
b101101 "
b101101 @
0$
b101000 %
b101000 >
1+
#456000
0/
12
b101001 1
b11111101 -
b11100 7
b0 ,
#460000
15
b101001 4
b101001 9
b1111111110000101 :
b11111101 (
b11111101 8
0*
0+
#465000
1!
b101001 "
b101001 @
b11111101 %
b11111101 >
1+
#466000
b1110000 1
b1100110 -
b11101 7
#470000
b1110000 4
b1110000 9
b10110010100000 :
b1100110 (
b1100110 8
0+
#475000
b1110000 "
b1110000 @
b1100110 %
b1100110 >
1+
#476000
b11010 1
b11010101 -
b11110 7
#480000
b11010 4
b11010 9
b1111101110100010 :
b11010101 (
b11010101 8
0+
#485000
b11010 "
b11010 @
b11010101 %
b11010101 >
1+
#486000
1.
b10110110 1
b100110 -
b11111 7
#490000
b10110110 4
b10110110 9
1)
b1111010100000100 :
b100110 (
b100110 8
0+
#495000
b11111111111111111111010100000100 #
b11111111111111111111010100000100 ?
b10110110 "
b10110110 @
1$
b100110 %
b100110 >
1+
#496000
0.
b11011011 1
b1111110 -
b100000 7
b11111111111111111111010100000100 ,
#500000
b11011011 4
b11011011 9
0)
b1110110111001010 :
b1111110 (
b1111110 8
0+
#505000
b11011011 "
b11011011 @
0$
b1111110 %
b1111110 >
1+
#506000
02
1.
b10100001 1
b10111 -
b100001 7
#510000
05
b10100001 4
b10100001 9
1)
b1111011101110111 :
b10111 (
b10111 8
0+
#515000
0!
b10100001 "
b10100001 @
1$
b10111 %
b10111 >
1+
#516000
0.
b11000001 1
b101001 -
b100010 7
#520000
b11000001 4
b11000001 9
0)
b1111010111101001 :
b101001 (
b101001 8
0+
#525000
b11000001 "
b11000001 @
0$
b101001 %
b101001 >
1+
#526000
1.
b10001010 1
b11101100 -
b100011 7
#530000
b10001010 4
b10001010 9
1)
b100100111000 :
b11101100 (
b11101100 8
0+
#535000
b10001010 "
b10001010 @
1$
b11101100 %
b11101100 >
1+
#536000
12
0.
b11100110 1
b1110 -
b100100 7
#540000
15
b11100110 4
b11100110 9
0)
b1111111010010100 :
b1110 (
b1110 8
0+
#545000
1!
b11100110 "
b11100110 @
0$
b1110 %
b1110 >
1+
#546000
b111000 1
b10011110 -
b100101 7
#550000
b111000 4
b111000 9
b1110101010010000 :
b10011110 (
b10011110 8
0+
#555000
b111000 "
b111000 @
b10011110 %
b10011110 >
1+
#556000
1.
b11000111 1
b1101011 -
b100110 7
#560000
b11000111 4
b11000111 9
1)
b1110100000101101 :
b1101011 (
b1101011 8
0+
#565000
b11111111111111111101110100110001 #
b11111111111111111101110100110001 ?
b11000111 "
b11000111 @
1$
b1101011 %
b1101011 >
1+
#566000
02
b10110100 1
b10010010 -
b100111 7
b11111111111111111101110100110001 ,
#570000
05
b10110100 4
b10110100 9
b10000010101000 :
b10010010 (
b10010010 8
0+
#575000
0!
b10110100 "
b10110100 @
b10010010 %
b10010010 >
1+
#576000
b10111101 1
b110010 -
b101000 7
#580000
b10111101 4
b10111101 9
b1111001011101010 :
b110010 (
b110010 8
0+
#585000
b10111101 "
b10111101 @
b110010 %
b110010 >
1+
#586000
0.
b10001110 1
b10100001 -
b101001 7
#590000
b10001110 4
b10001110 9
0)
b10101001001110 :
b10100001 (
b10100001 8
0+
#595000
b10001110 "
b10001110 @
0$
b10100001 %
b10100001 >
1+
#596000
12
b1110101 1
b110110 -
b101010 7
#600000
15
b1110101 4
b1110101 9
b1100010101110 :
b110110 (
b110110 8
0+
#605000
1!
b1110101 "
b1110101 @
b110110 %
b110110 >
1+
#606000
02
1.
b10010010 1
b10011011 -
b101011 7
#610000
05
b10010010 4
b10010010 9
1)
b10101101100110 :
b10011011 (
b10011011 8
0+
#615000
0!
b10010010 "
b10010010 @
1$
b10011011 %
b10011011 >
1+
#616000
12
b1101 1
b11110 -
b101100 7
#620000
15
b1101 4
b1101 9
b110000110 :
b11110 (
b11110 8
0+
#625000
b11111111111111111101111010110111 #
b11111111111111111101111010110111 ?
1!
b1101 "
b1101 @
b11110 %
b11110 >
1+
#626000
b111011 1
b1000001 -
b101101 7
b11111111111111111101111010110111 ,
#630000
b111011 4
b111011 9
b111011111011 :
b1000001 (
b1000001 8
0+
#635000
b11111111111111111110110110110010 #
b11111111111111111110110110110010 ?
b111011 "
b111011 @
b1000001 %
b1000001 >
1+
#636000
02
b100 1
b11100010 -
b101110 7
b11111111111111111110110110110010 ,
#640000
05
b100 4
b100 9
b1111111110001000 :
b11100010 (
b11100010 8
0+
#645000
0!
b100 "
b100 @
b11100010 %
b11100010 >
1+
#646000
12
0.
b11100101 1
b111001 -
b101111 7
#650000
15
b11100101 4
b11100101 9
0)
b1111100111111101 :
b111001 (
b111001 8
0+
#655000
1!
b11100101 "
b11100101 @
0$
b111001 %
b111001 >
1+
#656000
02
b10100001 1
b100111 -
b110000 7
#660000
05
b10100001 4
b10100001 9
b1111000110000111 :
b100111 (
b100111 8
0+
#665000
0!
b10100001 "
b10100001 @
b100111 %
b100111 >
1+
#666000
b10010 1
b10100 -
b110001 7
#670000
b10010 4
b10010 9
b101101000 :
b10100 (
b10100 8
0+
#675000
b10010 "
b10010 @
b10100 %
b10100 >
1+
#676000
1.
b11110101 1
b101011 -
b110010 7
#680000
b11110101 4
b11110101 9
1)
b1111111000100111 :
b101011 (
b101011 8
0+
